req.py
req-0.0.3.dist-info/DESCRIPTION.rst
req-0.0.3.dist-info/METADATA
req-0.0.3.dist-info/RECORD
req-0.0.3.dist-info/WHEEL
req-0.0.3.dist-info/metadata.json
req-0.0.3.dist-info/top_level.txt
